prometheus_client_gc/__init__.py
prometheus_client_gc/asgi.py
prometheus_client_gc/context_managers.py
prometheus_client_gc/core.py
prometheus_client_gc/decorator.py
prometheus_client_gc/exposition.py
prometheus_client_gc/gc_collector.py
prometheus_client_gc/metrics.py
prometheus_client_gc/metrics_core.py
prometheus_client_gc/mmap_dict.py
prometheus_client_gc/multiprocess.py
prometheus_client_gc/parser.py
prometheus_client_gc/platform_collector.py
prometheus_client_gc/process_collector.py
prometheus_client_gc/registry.py
prometheus_client_gc/samples.py
prometheus_client_gc/utils.py
prometheus_client_gc/values.py
prometheus_client_gc/bridge/__init__.py
prometheus_client_gc/bridge/graphite.py
prometheus_client_gc/openmetrics/__init__.py
prometheus_client_gc/openmetrics/exposition.py
prometheus_client_gc/openmetrics/parser.py
prometheus_client_gc/twisted/__init__.py
prometheus_client_gc/twisted/_exposition.py
prometheus_client_gc-0.9.1.dist-info/LICENSE
prometheus_client_gc-0.9.1.dist-info/METADATA
prometheus_client_gc-0.9.1.dist-info/NOTICE
prometheus_client_gc-0.9.1.dist-info/WHEEL
prometheus_client_gc-0.9.1.dist-info/top_level.txt
prometheus_client_gc-0.9.1.dist-info/RECORD
