Metadata-Version: 2.1
Name: prometheus-client-gc
Version: 0.9.1
Summary: Fully originated from the official client of Prometheus monitoring system with only directory renamed.
Home-page: https://github.com/prometheus/client_python
Author: Brian Brazil
Author-email: brian.brazil@robustperception.io
License: Apache Software License 2.0
Keywords: prometheus monitoring instrumentation client
Platform: UNKNOWN
Classifier: Development Status :: 4 - Beta
Classifier: Intended Audience :: Developers
Classifier: Intended Audience :: Information Technology
Classifier: Intended Audience :: System Administrators
Classifier: Programming Language :: Python
Classifier: Programming Language :: Python :: 2
Classifier: Programming Language :: Python :: 2.6
Classifier: Programming Language :: Python :: 2.7
Classifier: Programming Language :: Python :: 3
Classifier: Programming Language :: Python :: 3.4
Classifier: Programming Language :: Python :: 3.5
Classifier: Programming Language :: Python :: 3.6
Classifier: Programming Language :: Python :: 3.7
Classifier: Programming Language :: Python :: 3.8
Classifier: Programming Language :: Python :: 3.9
Classifier: Programming Language :: Python :: Implementation :: CPython
Classifier: Programming Language :: Python :: Implementation :: PyPy
Classifier: Topic :: System :: Monitoring
Classifier: License :: OSI Approved :: Apache Software License
Provides-Extra: twisted
Requires-Dist: twisted ; extra == 'twisted'
